stacking_pr/__init__.py
stacking_pr/cli.py
stacking_pr/version.py
stacking_pr/commands/__init__.py
stacking_pr/commands/create.py
stacking_pr/commands/init.py
stacking_pr/commands/merge.py
stacking_pr/commands/push.py
stacking_pr/commands/rebase.py
stacking_pr/commands/status.py
stacking_pr/utils/__init__.py
stacking_pr/utils/config.py
stacking_pr/utils/git.py
stacking_pr/utils/git_errors.py
stacking_pr/utils/github.py
stacking_pr/utils/stack.py
stacking_pr/utils/validation.py
stacking_pr-0.3.0.dist-info/licenses/LICENSE
stacking_pr-0.3.0.dist-info/METADATA
stacking_pr-0.3.0.dist-info/WHEEL
stacking_pr-0.3.0.dist-info/entry_points.txt
stacking_pr-0.3.0.dist-info/top_level.txt
stacking_pr-0.3.0.dist-info/RECORD
