Metadata-Version: 2.4
Name: stacking-pr
Version: 0.3.0
Summary: A developer tool for managing clean commit history and modular PRs
Author-email: Hitesh Arora <hitesh.arora1997@gmail.com>
License-Expression: MIT
Project-URL: Homepage, https://github.com/hitesharora1997/stacking-pr
Project-URL: Documentation, https://github.com/hitesharora1997/stacking-pr#readme
Project-URL: Repository, https://github.com/hitesharora1997/stacking-pr
Project-URL: Issues, https://github.com/hitesharora1997/stacking-pr/issues
Keywords: git,github,pull-request,workflow,developer-tools,cli
Classifier: Development Status :: 4 - Beta
Classifier: Intended Audience :: Developers
Classifier: Programming Language :: Python :: 3
Classifier: Programming Language :: Python :: 3.9
Classifier: Programming Language :: Python :: 3.10
Classifier: Programming Language :: Python :: 3.11
Classifier: Programming Language :: Python :: 3.12
Classifier: Operating System :: OS Independent
Classifier: Environment :: Console
Classifier: Topic :: Software Development :: Version Control :: Git
Requires-Python: >=3.9
License-File: LICENSE
Requires-Dist: click>=8.0.0
Requires-Dist: PyYAML>=6.0
Requires-Dist: rich>=13.0.0
Provides-Extra: dev
Requires-Dist: black==25.1.0; extra == "dev"
Requires-Dist: flake8==7.2.0; extra == "dev"
Requires-Dist: isort==6.0.1; extra == "dev"
Requires-Dist: mypy>=1.0.0; extra == "dev"
Provides-Extra: test
Requires-Dist: pytest==8.3.4; extra == "test"
Requires-Dist: pytest-cov==6.0.0; extra == "test"
Requires-Dist: pytest-mock>=3.10.0; extra == "test"
Dynamic: license-file
